README.rst
setup.py
django_selenium_boilerplate.egg-info/PKG-INFO
django_selenium_boilerplate.egg-info/SOURCES.txt
django_selenium_boilerplate.egg-info/dependency_links.txt
django_selenium_boilerplate.egg-info/requires.txt
django_selenium_boilerplate.egg-info/top_level.txt
selenium_boilerplate/__init__.py