Metadata-Version: 1.1
Name: django-selenium-boilerplate
Version: 0.0.2
Summary: Boilerplate for setting up selenium tests in Django
Home-page: https://github.com/yourcelf/django-selenium-boilerplate.git
Author: Charlie DeTar
Author-email: cfd@media.mit.edu
License: BSD License
Platform: UNKNOWN
Classifier: Environment :: Web Environment
Classifier: Framework :: Django
Classifier: Intended Audience :: Developers
Classifier: License :: OSI Approved :: BSD License
Classifier: Operating System :: OS Independent
Classifier: Programming Language :: Python
Classifier: Topic :: Internet :: WWW/HTTP
Classifier: Topic :: Internet :: WWW/HTTP :: Dynamic Content
